./.gitignore
./PKG-INFO
./README.md
./pyproject.toml
./uv.lock
./.github/workflows/publish-to-pypi.yml
./sqlalchemy_pg_access/alembic.py
./sqlalchemy_pg_access/grant.py
./sqlalchemy_pg_access/policy.py
./sqlalchemy_pg_access/registry.py
./tests/conftest.py
./tests/test_policy_compilation.py
./tests/test_policy_decorator.py
sqlalchemy_pg_access-0.1.4.dist-info/METADATA
sqlalchemy_pg_access-0.1.4.dist-info/WHEEL
sqlalchemy_pg_access-0.1.4.dist-info/RECORD
