Metadata-Version: 2.4
Name: sqlalchemy-pg-access
Version: 0.1.4
Summary: Manage Postgres RLS policies in SQLAlchemy
Author-email: John Harrington <jharr92@gmail.com>
Requires-Python: >=3.11
Requires-Dist: sqlalchemy>=2.0.39
Provides-Extra: alembic
Requires-Dist: alembic>=1.15.1; extra == 'alembic'
